resage/__init__.py
resage/colyear/__init__.py
resage/colyear/abs.py
resage/colyear/colyear.py
resage/rad2/Rad2.py
resage/rad2/__init__.py
resage/rad2/abs.py
resage/radical/__init__.py
resage/radical/abs.py
resage/radical/radical.py
resages/__init__.py
resages/abs.py
resages/colyear.py
resages/rad2.py
resages/radical.py
resages/colyear/__init__.py
resages/colyear/abs.py
resages/colyear/colyear.py
resages/rad2/Rad2.py
resages/rad2/__init__.py
resages/rad2/abs.py
resages/radical/__init__.py
resages/radical/abs.py
resages/radical/radical.py
resages-0.22.dist-info/LICENSE
resages-0.22.dist-info/METADATA
resages-0.22.dist-info/WHEEL
resages-0.22.dist-info/top_level.txt
resages-0.22.dist-info/RECORD
