Metadata-Version: 2.1
Name: resages
Version: 0.22
Summary: Methods and codes for reservoir atmosphere 14C age offset calculations
Home-page: https://github.com/cccchou/radcal
Author: Alex_chou
Author-email: alex_chou@sjtu.edu.com
Classifier: Programming Language :: Python :: 3
Classifier: License :: OSI Approved :: MIT License
Classifier: Operating System :: OS Independent
Requires-Python: >=3.10
License-File: LICENSE
Requires-Dist: numpy
Requires-Dist: pandas
Requires-Dist: scipy
Requires-Dist: tqdm
